abstract_modules/__init__.py
abstract_modules/create_module.py
abstract_modules/create_module_folder.py
abstract_modules/get_readme.py
abstract_modules/main.py
abstract_modules/module_utils.py
abstract_modules/pypit.py
abstract_modules/trace_module.py
abstract_modules/upload_utils.py
abstract_modules-0.0.3.92.dist-info/METADATA
abstract_modules-0.0.3.92.dist-info/WHEEL
abstract_modules-0.0.3.92.dist-info/top_level.txt
abstract_modules-0.0.3.92.dist-info/RECORD
